{
  "world_id": "world-1",
  "tick": 0,
  "time": "1970-01-01T00:00:00.000Z",
  "config": {
    "language": "zh"
  },
  "environment": {
    "description": "calm"
  },
  "social_context": {
    "macro_events": [],
    "narratives": [],
    "pressures": [],
    "institutions": [],
    "ambient_noise": []
  },
  "agents": {
    "director": {
      "kind": "world",
      "id": "director-1"
    },
    "creator": {
      "kind": "persona",
      "id": "creator-1"
    },
    "personal": {
      "kind": "personal",
      "life_status": "alive",
      "genetics": {
        "seed": "default-user"
      },
      "identity": {
        "name": "user"
      },
      "memory_short": [],
      "memory_long": [],
      "vitals": {
        "energy": 0.7,
        "stress": 0.2,
        "sleep_debt": 0.1,
        "focus": 0.6,
        "aging_index": 0.1
      },
      "emotion": {
        "label": "neutral",
        "intensity": 0.2
      },
      "persona": {
        "openness": 0.5,
        "stability": 0.5,
        "attachment": 0.5,
        "agency": 0.5,
        "empathy": 0.5
      },
      "goals": [],
      "relations": {},
      "action_history": []
    },
    "social": {
      "kind": "social",
      "id": "social-1"
    },
    "npcs": []
  },
  "narratives": {
    "patterns": [],
    "arcs": [],
    "summaries": [],
    "stats": {
      "total_patterns": 0,
      "active_patterns": 0,
      "concluded_patterns": 0,
      "total_arcs": 0,
      "completed_arcs": 0
    }
  },
  "events": [],
  "relations": {},
  "active_hooks": [],
  "systems": {}
}